status_checker_api/__init__.py
status_checker_api/__main__.py
tests/__init__.py
tests/test_status_checker_api.py
api_status_checker-0.3.dist-info/LICENSE
api_status_checker-0.3.dist-info/METADATA
api_status_checker-0.3.dist-info/WHEEL
api_status_checker-0.3.dist-info/entry_points.txt
api_status_checker-0.3.dist-info/top_level.txt
api_status_checker-0.3.dist-info/RECORD
