Metadata-Version: 2.1
Name: api_status_checker
Version: 0.3
Summary: Un paquete para verificar el estado de una API.
Home-page: https://github.com/statick88/api_status_checker
Author: Diego Saavedra
Author-email: dsaavedra88@gmail.com
Classifier: Programming Language :: Python :: 3
Classifier: License :: OSI Approved :: MIT License
Classifier: Operating System :: OS Independent
Requires-Python: >=3.12
License-File: LICENSE
Requires-Dist: requests
